netstealth_analyzer/__init__.py
netstealth_analyzer/_version.py
netstealth_analyzer/core.py
netstealth_analyzer/models.py
netstealth_analyzer/utils.py
netstealth_analyzer/detectors/__init__.py
netstealth_analyzer/detectors/browser.py
netstealth_analyzer/detectors/network.py
netstealth_analyzer/detectors/proxy.py
netstealth_analyzer/detectors/tls.py
netstealth_analyzer/parsers/__init__.py
netstealth_analyzer/parsers/browser.py
netstealth_analyzer/parsers/har.py
netstealth_analyzer/parsers/mitmproxy.py
netstealth_analyzer/parsers/poc.py
netstealth_analyzer/reports/__init__.py
netstealth_analyzer/reports/summary.py
netstealth_analyzer-0.1.0.dist-info/METADATA
netstealth_analyzer-0.1.0.dist-info/WHEEL
netstealth_analyzer-0.1.0.dist-info/entry_points.txt
netstealth_analyzer-0.1.0.dist-info/RECORD
