Metadata-Version: 2.4
Name: netstealth-analyzer
Version: 0.1.0
Summary: Advanced log analyzer for network stealth operations - detects TLS fingerprint issues, proxy indicators, and security red flags
Project-URL: Homepage, https://github.com/netstealth/netstealth-analyzer
Project-URL: Repository, https://github.com/netstealth/netstealth-analyzer
Project-URL: Issues, https://github.com/netstealth/netstealth-analyzer/issues
Project-URL: Documentation, https://netstealth-analyzer.readthedocs.io/
Author-email: NetStealth Contributors <contributors@netstealth.com>
License: MIT
Keywords: analyzer,fingerprint,mitmproxy,network,proxy,stealth,tls
Classifier: Development Status :: 4 - Beta
Classifier: Intended Audience :: Developers
Classifier: License :: OSI Approved :: MIT License
Classifier: Operating System :: OS Independent
Classifier: Programming Language :: Python :: 3
Classifier: Programming Language :: Python :: 3.8
Classifier: Programming Language :: Python :: 3.9
Classifier: Programming Language :: Python :: 3.10
Classifier: Programming Language :: Python :: 3.11
Classifier: Programming Language :: Python :: 3.12
Classifier: Topic :: Internet :: Proxy Servers
Classifier: Topic :: Security
Classifier: Topic :: System :: Logging
Requires-Python: >=3.8
Requires-Dist: jsonschema>=4.0.0
Requires-Dist: pydantic>=2.0.0
Requires-Dist: python-dateutil>=2.8.0
Requires-Dist: pyyaml>=6.0
Requires-Dist: requests>=2.28.0
Requires-Dist: rich>=13.0.0
Requires-Dist: tabulate>=0.9.0
Provides-Extra: dev
Requires-Dist: black>=23.0.0; extra == 'dev'
Requires-Dist: flake8>=6.0.0; extra == 'dev'
Requires-Dist: isort>=5.12.0; extra == 'dev'
Requires-Dist: mypy>=1.5.0; extra == 'dev'
Requires-Dist: pre-commit>=3.0.0; extra == 'dev'
Requires-Dist: pytest-cov>=4.0.0; extra == 'dev'
Requires-Dist: pytest>=7.0.0; extra == 'dev'
Provides-Extra: full
Requires-Dist: beautifulsoup4>=4.12.0; extra == 'full'
Requires-Dist: har2tree>=1.0.0; extra == 'full'
Requires-Dist: matplotlib>=3.7.0; extra == 'full'
Requires-Dist: pandas>=2.0.0; extra == 'full'
Requires-Dist: plotly>=5.15.0; extra == 'full'
Provides-Extra: integration
